napalm_fsos_ssh/__init__.py
napalm_fsos_ssh/fsos.py
napalm_fsos_ssh/utils/textfsm_templates/index
napalm_fsos_ssh/utils/textfsm_templates/ping.textfsm
napalm_fsos_ssh/utils/textfsm_templates/show_arp.textfsm
napalm_fsos_ssh/utils/textfsm_templates/show_interfaces_brief.textfsm
napalm_fsos_ssh/utils/textfsm_templates/show_interfaces_counters.textfsm
napalm_fsos_ssh/utils/textfsm_templates/show_ip_interface_brief.textfsm
napalm_fsos_ssh/utils/textfsm_templates/show_ip_route.textfsm
napalm_fsos_ssh/utils/textfsm_templates/show_ipv6_interface_brief.textfsm
napalm_fsos_ssh/utils/textfsm_templates/show_ipv6_neighbors.textfsm
napalm_fsos_ssh/utils/textfsm_templates/show_ipv6_route.textfsm
napalm_fsos_ssh/utils/textfsm_templates/show_lldp_neighbor.textfsm
napalm_fsos_ssh/utils/textfsm_templates/show_lldp_neighbor_interface.textfsm
napalm_fsos_ssh/utils/textfsm_templates/show_memory.textfsm
napalm_fsos_ssh/utils/textfsm_templates/show_ntp.textfsm
napalm_fsos_ssh/utils/textfsm_templates/show_snmp_server.textfsm
napalm_fsos_ssh/utils/textfsm_templates/show_snmp_server_engine_id.textfsm
napalm_fsos_ssh/utils/textfsm_templates/show_system.textfsm
napalm_fsos_ssh/utils/textfsm_templates/show_transceiver.textfsm
napalm_fsos_ssh/utils/textfsm_templates/show_users.textfsm
napalm_fsos_ssh/utils/textfsm_templates/show_version.textfsm
napalm_fsos_ssh/utils/textfsm_templates/show_vlan_all.textfsm
napalm_fsos_ssh/utils/textfsm_templates/traceroute.textfsm
napalm_fsos_ssh-1.3.0.dist-info/METADATA
napalm_fsos_ssh-1.3.0.dist-info/WHEEL
napalm_fsos_ssh-1.3.0.dist-info/licenses/LICENSE
napalm_fsos_ssh-1.3.0.dist-info/licenses/LICENSE.fr
napalm_fsos_ssh-1.3.0.dist-info/RECORD
