Metadata-Version: 2.3
Name: napalm-fsos-ssh
Version: 1.3.0
Summary: Napalm driver for FSOS through SSH
Project-URL: Homepage, https://github.com/napalm-automation-community/napalm-fsos-ssh
Project-URL: Repository, https://github.com/napalm-automation-community/napalm-fsos-ssh
Project-URL: Issues, https://github.com/napalm-automation-community/napalm-fsos-ssh/issues
Author-email: Ludovic Ortega <ludovic.ortega@adminafk.fr>
License-File: LICENSE
License-File: LICENSE.fr
Keywords: fsos,napalm,netmiko
Classifier: License :: OSI Approved :: CEA CNRS Inria Logiciel Libre License, version 2.1 (CeCILL-2.1)
Classifier: Operating System :: OS Independent
Classifier: Programming Language :: Python
Classifier: Programming Language :: Python :: 3.9
Classifier: Programming Language :: Python :: 3.10
Classifier: Programming Language :: Python :: 3.11
Classifier: Programming Language :: Python :: 3.12
Classifier: Programming Language :: Python :: 3.13
Classifier: Topic :: Utilities
Requires-Python: <4.0.0,>=3.9
Requires-Dist: napalm<5.1,>=4.0
Provides-Extra: dev
Requires-Dist: pytest-cov~=5.0.0; extra == 'dev'
Requires-Dist: pytest~=8.3.3; extra == 'dev'
Requires-Dist: ruff~=0.7.0; extra == 'dev'
